archiver/__init__.py
archiver/__main__.py
archiver/cli.py
archiver/git_manager.py
archiver/granola_fetcher.py
archiver/main.py
archiver/markdown_formatter.py
archiver/models.py
archiver/state_tracker.py
granola_archiver-0.3.0.dist-info/METADATA
granola_archiver-0.3.0.dist-info/WHEEL
granola_archiver-0.3.0.dist-info/entry_points.txt
granola_archiver-0.3.0.dist-info/licenses/LICENSE
granola_archiver-0.3.0.dist-info/RECORD
