Metadata-Version: 2.4
Name: granola-archiver
Version: 0.3.0
Summary: Automated system to archive Granola meeting transcripts to GitHub
Project-URL: Homepage, https://github.com/anjor/granola-archiver
Project-URL: Repository, https://github.com/anjor/granola-archiver
Author: Anjor Kanekar
License: MIT
License-File: LICENSE
Classifier: Intended Audience :: Developers
Classifier: License :: OSI Approved :: MIT License
Classifier: Operating System :: OS Independent
Classifier: Programming Language :: Python :: 3.13
Requires-Python: >=3.13
Requires-Dist: gitpython>=3.1
Requires-Dist: granola-client>=0.3.0
Requires-Dist: httpx>=0.25.0
Requires-Dist: pydantic>=2.0
Requires-Dist: python-dotenv>=1.0
Requires-Dist: pyyaml>=6.0
Requires-Dist: rich>=13.0
Provides-Extra: dev
Requires-Dist: black>=23.0; extra == 'dev'
Requires-Dist: pytest-asyncio>=0.20; extra == 'dev'
Requires-Dist: pytest>=7.0; extra == 'dev'
Requires-Dist: ruff>=0.1.0; extra == 'dev'
